hello_world_tool_package/__init__.py
hello_world_tool_package/tools/__init__.py
hello_world_tool_package/tools/hello_world_tool.py
hello_world_tool_package/tools/hello_world_tool_2.py
hello_world_tool_package/tools/hello_world_tool_3.py
hello_world_tool_package/tools/utils.py
hello_world_tool_package/yamls/hello_world_tool.yaml
hello_world_tool_package/yamls/hello_world_tool_2.yaml
hello_world_tool_package/yamls/hello_world_tool_3.yaml
tests/__init__.py
tests/test_hello_world_tool.py
hello_world_tool_package-0.0.1.dist-info/METADATA
hello_world_tool_package-0.0.1.dist-info/WHEEL
hello_world_tool_package-0.0.1.dist-info/entry_points.txt
hello_world_tool_package-0.0.1.dist-info/top_level.txt
hello_world_tool_package-0.0.1.dist-info/RECORD
