Metadata-Version: 2.1
Name: hello-world-tool-package
Version: 0.0.1
Summary: This is my tools package
